pygraphile/__init__.py
pygraphile/py.typed
pygraphile-0.1.0.dist-info/METADATA
pygraphile-0.1.0.dist-info/WHEEL
pygraphile-0.1.0.dist-info/licenses/LICENSE
pygraphile-0.1.0.dist-info/RECORD
