Metadata-Version: 2.4
Name: pygraphile
Version: 0.1.0
Summary: A Python library inspired by PostGraphile - automatically generates GraphQL APIs from databases. Currently supports SQLite with plans for additional database support.
Project-URL: Homepage, https://github.com/dshaw0004/pygraphile
Project-URL: Repository, https://github.com/dshaw0004/pygraphile
Project-URL: Issues, https://github.com/dshaw0004/pygraphile/issues
Author: dshaw0004
License: MIT
License-File: LICENSE
Keywords: api,database,graphql,postgraphile,sqlite
Classifier: Development Status :: 3 - Alpha
Classifier: Intended Audience :: Developers
Classifier: License :: OSI Approved :: MIT License
Classifier: Programming Language :: Python :: 3
Classifier: Programming Language :: Python :: 3.9
Classifier: Programming Language :: Python :: 3.10
Classifier: Programming Language :: Python :: 3.11
Classifier: Programming Language :: Python :: 3.12
Classifier: Programming Language :: Python :: 3.13
Classifier: Topic :: Database
Classifier: Topic :: Software Development :: Libraries :: Python Modules
Requires-Python: >=3.9
